pretty_print_hydra-0.1.0.dist-info/METADATA
pretty_print_hydra-0.1.0.dist-info/WHEEL
pretty_print_hydra-0.1.0.dist-info/licenses/LICENSE
pretty_print_hydra/__init__.py
pretty_print_hydra/__main__.py
pretty_print_hydra/cli.py
pretty_print_hydra/hydra.py
pretty_print_hydra/pretty.py
pretty_print_hydra-0.1.0.dist-info/RECORD
