Metadata-Version: 2.1
Name: pretty-print-hydra
Version: 0.1.0
Summary: Pretty print Hydra configs for easier debugging in development.
Author-Email: Amit Parekh <amit@amitkparekh.com>
License: MIT
Classifier: Programming Language :: Python :: 3
Classifier: Programming Language :: Python :: 3.10
Classifier: Programming Language :: Python :: 3.11
Classifier: Programming Language :: Python :: 3.12
Classifier: Development Status :: 2 - Pre-Alpha
Classifier: Typing :: Typed
Requires-Python: >=3.10
Requires-Dist: hydra-core>=1.3.0
Requires-Dist: rich>=13.0.0
Requires-Dist: omegaconf>=2.3.0
